pypatchin/__init__.py
pypatchin/compare.py
pypatchin/patch.py
pypatchin-0.0.3.dist-info/LICENSE
pypatchin-0.0.3.dist-info/METADATA
pypatchin-0.0.3.dist-info/WHEEL
pypatchin-0.0.3.dist-info/top_level.txt
pypatchin-0.0.3.dist-info/RECORD
