Metadata-Version: 2.1
Name: pypatchin
Version: 0.0.3
Summary: Do you want a fast and clean solution to patch your files and repositories? Use Python pypatchin package!
Home-page: https://github.com/giuliapuntoit/pypatch
Author: Giulia Milan
Author-email: giuliapuntoit96@gmail.com
Maintainer: Giulia Milan
Maintainer-email: giuliapuntoit96@gmail.com
License: GNU GENERAL PUBLIC LICENSE v3
Download-URL: https://github.com/giuliapuntoit/pypatch.git
Keywords: python,patch
Platform: UNKNOWN
Requires-Dist: diff-match-patch
Requires-Dist: pypandoc
